autoresumex/__init__.py
autoresumex/generator.py
autoresumex/utils.py
autoresumex-0.1.0.dist-info/licenses/License
autoresumex-0.1.0.dist-info/METADATA
autoresumex-0.1.0.dist-info/WHEEL
autoresumex-0.1.0.dist-info/top_level.txt
autoresumex-0.1.0.dist-info/RECORD
