Metadata-Version: 2.4
Name: autoresumex
Version: 0.1.0
Summary: Automatically generate ATS-friendly resumes as PDF or Markdown.
Home-page: https://www.linkedin.com/in/ganeshamoorthy-s-8466b7332
Author: Ganeshamoorthy
Author-email: Ganeshamoorthy <ganeshms1110@gmail.com>
Project-URL: Homepage, https://www.linkedin.com/in/ganeshamoorthy-s-8466b7332
Requires-Python: >=3.8
License-File: License
Requires-Dist: jinja2
Requires-Dist: markdown2
Requires-Dist: weasyprint
Dynamic: license-file
